lib/__init__.py
lib/meli.py
lib/ssl_helper.py
mlapi-1.3.8.data/scripts/mlapi.py
test/__init__.py
test/main.py
mlapi-1.3.8.dist-info/LICENSE
mlapi-1.3.8.dist-info/METADATA
mlapi-1.3.8.dist-info/WHEEL
mlapi-1.3.8.dist-info/top_level.txt
mlapi-1.3.8.dist-info/RECORD
