Metadata-Version: 2.1
Name: mlapi
Version: 1.3.8
Summary: Mercado Livre API
Home-page: https://github.com/mercadolibre/python-sdk
Author: João Paulo de Melo
Author-email: jpmdik@gmail.com
License: UNKNOWN
Platform: UNKNOWN
Classifier: Programming Language :: Python :: 3
Classifier: License :: OSI Approved :: MIT License
Classifier: Operating System :: OS Independent
Requires-Dist: configparser
